{"questions": [{"player_1": {"name": "Shaun Pollock", "player_stat": 27.36}, "player_2": {"name": "Yuzvendra Chahal", "player_stat": 22.52}, "stat": "average", "skill": "BOWL", "question_text": "Who has the better bowling average?", "greater": false}, {"player_1": {"name": "Brett Lee", "player_stat": 1095.0}, "player_2": {"name": "Mitchell Johnson", "player_stat": 1702.0}, "stat": "runs_given", "skill": "BOWL", "question_text": "Who has given away less runs?", "greater": false}, {"player_1": {"name": "RP Singh", "player_stat": 19.7}, "player_2": {"name": "Shane Warne", "player_stat": 20.9}, "stat": "strike_rate", "skill": "BOWL", "question_text": "Who has the lower bowling strike rate?", "greater": false}, {"player_1": {"name": "Martin Guptill", "player_stat": 50.0}, "player_2": {"name": "Manish Pandey", "player_stat": 114.0}, "stat": "highest", "skill": "BAT", "question_text": "Who has the greater highest score?", "greater": true}, {"player_1": {"name": "James Faulkner", "player_stat": 1778.0}, "player_2": {"name": "Chaminda Vaas", "player_stat": 355.0}, "stat": "runs_given", "skill": "BOWL", "question_text": "Who has given away less runs?", "greater": false}, {"player_1": {"name": "Faf du Plessis", "player_stat": 0.0}, "player_2": {"name": "AB de Villiers", "player_stat": 3.0}, "stat": "hundreds", "skill": "BAT", "question_text": "Who has scored more hundreds?", "greater": true}, {"player_1": {"name": "Manish Pandey", "player_stat": 264.0}, "player_2": {"name": "Michael Hussey", "player_stat": 198.0}, "stat": "fours", "skill": "BAT", "question_text": "Who has hit more fours?", "greater": true}, {"player_1": {"name": "Ashish Reddy", "player_stat": 17.0}, "player_2": {"name": "Adam Gilchrist", "player_stat": 239.0}, "stat": "fours", "skill": "BAT", "question_text": "Who has hit more fours?", "greater": true}, {"player_1": {"name": "Praveen Kumar", "player_stat": 90.0}, "player_2": {"name": "Bhuvneshwar Kumar", "player_stat": 136.0}, "stat": "wickets", "skill": "BOWL", "question_text": "Who has taken more wickets?", "greater": true}, {"player_1": {"name": "Devdutt Padikkal", "player_stat": 43.5}, "player_2": {"name": "Harbhajan Singh", "player_stat": 15.64}, "stat": "average", "skill": "BAT", "question_text": "Who has the better batting average?", "greater": true}, {"player_1": {"name": "Wayne Parnell", "player_stat": 26.96}, "player_2": {"name": "Krunal Pandya", "player_stat": 29.16}, "stat": "average", "skill": "BOWL", "question_text": "Who has the better bowling average?", "greater": false}, {"player_1": {"name": "Khaleel Ahmed", "player_stat": 13.9}, "player_2": {"name": "Doug Bollinger", "player_stat": 15.5}, "stat": "strike_rate", "skill": "BOWL", "question_text": "Who has the lower bowling strike rate?", "greater": false}, {"player_1": {"name": "Harbhajan Singh", "player_stat": 22.4}, "player_2": {"name": "Daniel Vettori", "player_stat": 27.7}, "stat": "strike_rate", "skill": "BOWL", "question_text": "Who has the lower bowling strike rate?", "greater": false}, {"player_1": {"name": "Morne Morkel", "player_stat": 2089.0}, "player_2": {"name": "Roelof van der Merwe", "player_stat": 498.0}, "stat": "runs_given", "skill": "BOWL", "question_text": "Who has given away less runs?", "greater": false}, {"player_1": {"name": "Anil Kumble", "player_stat": 21.4}, "player_2": {"name": "Irfan Pathan", "player_stat": 25.5}, "stat": "strike_rate", "skill": "BOWL", "question_text": "Who has the lower bowling strike rate?", "greater": false}, {"player_1": {"name": "Samuel Badree", "player_stat": 23.4}, "player_2": {"name": "Imran Tahir", "player_stat": 15.5}, "stat": "strike_rate", "skill": "BOWL", "question_text": "Who has the lower bowling strike rate?", "greater": false}, {"player_1": {"name": "Adam Zampa", "player_stat": 13.1}, "player_2": {"name": "Azhar Mahmood", "player_stat": 18.5}, "stat": "strike_rate", "skill": "BOWL", "question_text": "Who has the lower bowling strike rate?", "greater": false}, {"player_1": {"name": "Jonny Bairstow", "player_stat": 47.0}, "player_2": {"name": "Lendl Simmons", "player_stat": 39.96}, "stat": "average", "skill": "BAT", "question_text": "Who has the better batting average?", "greater": true}, {"player_1": {"name": "Sanath Jayasuriya", "player_stat": 1.0}, "player_2": {"name": "Nitish Rana", "player_stat": 0.0}, "stat": "hundreds", "skill": "BAT", "question_text": "Who has scored more hundreds?", "greater": true}, {"player_1": {"name": "Suresh Raina", "player_stat": 1.0}, "player_2": {"name": "Virat Kohli", "player_stat": 5.0}, "stat": "hundreds", "skill": "BAT", "question_text": "Who has scored more hundreds?", "greater": true}]}