{"questions": [{"player_1": {"name": "MS Dhoni", "player_stat": 84.0}, "player_2": {"name": "Manish Pandey", "player_stat": 114.0}, "stat": "highest", "skill": "BAT", "question_text": "Who has the greater highest score?", "greater": true}, {"player_1": {"name": "Ashish Nehra", "player_stat": 7.84}, "player_2": {"name": "Yusuf Pathan", "player_stat": 7.4}, "stat": "economy", "skill": "BOWL", "question_text": "Who has the better economy rate?", "greater": false}, {"player_1": {"name": "Irfan Pathan", "player_stat": 25.5}, "player_2": {"name": "Jaydev Unadkat", "player_stat": 20.2}, "stat": "strike_rate", "skill": "BOWL", "question_text": "Who has the better bowling strike rate?", "greater": false}, {"player_1": {"name": "Mitchell Johnson", "player_stat": 20.1}, "player_2": {"name": "Anil Kumble", "player_stat": 21.4}, "stat": "strike_rate", "skill": "BOWL", "question_text": "Who has the better bowling strike rate?", "greater": false}, {"player_1": {"name": "David Warner", "player_stat": 472.0}, "player_2": {"name": "Shane Watson", "player_stat": 357.0}, "stat": "fours", "skill": "BAT", "question_text": "Who has hit more fours?", "greater": true}, {"player_1": {"name": "MS Dhoni", "player_stat": 213.0}, "player_2": {"name": "Nitish Rana", "player_stat": 66.0}, "stat": "sixes", "skill": "BAT", "question_text": "Who has hit more sixes?", "greater": true}, {"player_1": {"name": "Rajat Bhatia", "player_stat": 28.45}, "player_2": {"name": "Doug Bollinger", "player_stat": 18.72}, "stat": "average", "skill": "BOWL", "question_text": "Who has the better bowling average?", "greater": false}, {"player_1": {"name": "Yuvraj Singh", "player_stat": 36.0}, "player_2": {"name": "Johan Botha", "player_stat": 25.0}, "stat": "wickets", "skill": "BOWL", "question_text": "Who has taken more wickets?", "greater": true}, {"player_1": {"name": "Krunal Pandya", "player_stat": 0.0}, "player_2": {"name": "Mohit Sharma", "player_stat": 0.0}, "stat": "maidens", "skill": "BOWL", "question_text": "Who has bowled more maidens?", "greater": true}, {"player_1": {"name": "Yuvraj Singh", "player_stat": 7.43}, "player_2": {"name": "Nathan Coulter-Nile", "player_stat": 7.66}, "stat": "economy", "skill": "BOWL", "question_text": "Who has the better economy rate?", "greater": false}, {"player_1": {"name": "Ravindra Jadeja", "player_stat": 29.94}, "player_2": {"name": "Ben Hilfenhaus", "player_stat": 21.77}, "stat": "average", "skill": "BOWL", "question_text": "Who has the better bowling average?", "greater": false}, {"player_1": {"name": "Ravi Bopara", "player_stat": 117.21}, "player_2": {"name": "Ben Cutting", "player_stat": 168.79}, "stat": "strike_rate", "skill": "BAT", "question_text": "Who has the better batting strike rate?", "greater": true}, {"player_1": {"name": "Shahbaz Nadeem", "player_stat": 1570.0}, "player_2": {"name": "Murali Kartik", "player_stat": 1388.0}, "stat": "runs_given", "skill": "BOWL", "question_text": "Who has given away less runs?", "greater": false}, {"player_1": {"name": "Vijay Shankar", "player_stat": 24.0}, "player_2": {"name": "Harbhajan Singh", "player_stat": 42.0}, "stat": "sixes", "skill": "BAT", "question_text": "Who has hit more sixes?", "greater": true}, {"player_1": {"name": "Shreyas Iyer", "player_stat": 76.0}, "player_2": {"name": "Andrew Symonds", "player_stat": 41.0}, "stat": "sixes", "skill": "BAT", "question_text": "Who has hit more sixes?", "greater": true}, {"player_1": {"name": "Dwayne Bravo", "player_stat": 17.9}, "player_2": {"name": "Chaminda Vaas", "player_stat": 15.6}, "stat": "strike_rate", "skill": "BOWL", "question_text": "Who has the better bowling strike rate?", "greater": false}, {"player_1": {"name": "Albie Morkel", "player_stat": 2359.0}, "player_2": {"name": "Mohit Sharma", "player_stat": 2470.0}, "stat": "runs_given", "skill": "BOWL", "question_text": "Who has given away less runs?", "greater": false}, {"player_1": {"name": "Dwayne Bravo", "player_stat": 2.0}, "player_2": {"name": "Iqbal Abdulla", "player_stat": 1.0}, "stat": "maidens", "skill": "BOWL", "question_text": "Who has bowled more maidens?", "greater": true}, {"player_1": {"name": "Chaminda Vaas", "player_stat": 7.55}, "player_2": {"name": "Sreenath Aravind", "player_stat": 8.2}, "stat": "economy", "skill": "BOWL", "question_text": "Who has the better economy rate?", "greater": false}, {"player_1": {"name": "Ali Murtaza", "player_stat": 29.3}, "player_2": {"name": "Ravi Rampaul", "player_stat": 18.7}, "stat": "strike_rate", "skill": "BOWL", "question_text": "Who has the better bowling strike rate?", "greater": false}]}