{"questions": [{"player_1": {"name": "Ryan Harris", "player_stat": 45.0}, "player_2": {"name": "Doug Bollinger", "player_stat": 37.0}, "stat": "wickets", "skill": "BOWL", "question_text": "Who has taken more wickets?", "greater": true}, {"player_1": {"name": "Shubman Gill", "player_stat": 0.0}, "player_2": {"name": "Colin de Grandhomme", "player_stat": 0.0}, "stat": "hundreds", "skill": "BAT", "question_text": "Who has scored more hundreds?", "greater": true}, {"player_1": {"name": "Ambati Rayudu", "player_stat": 285.0}, "player_2": {"name": "Michael Lumb", "player_stat": 45.0}, "stat": "fours", "skill": "BAT", "question_text": "Who has hit more fours?", "greater": true}, {"player_1": {"name": "Ramesh Powar", "player_stat": 7.42}, "player_2": {"name": "Zaheer Khan", "player_stat": 7.58}, "stat": "economy", "skill": "BOWL", "question_text": "Who has the better economy rate?", "greater": false}, {"player_1": {"name": "S Badrinath", "player_stat": 0.0}, "player_2": {"name": "Quinton de Kock", "player_stat": 1.0}, "stat": "hundreds", "skill": "BAT", "question_text": "Who has scored more hundreds?", "greater": true}, {"player_1": {"name": "Michael Lumb", "player_stat": 1.0}, "player_2": {"name": "Ravi Bopara", "player_stat": 3.0}, "stat": "fifties", "skill": "BAT", "question_text": "Who has scored more fifties?", "greater": true}, {"player_1": {"name": "Anil Kumble", "player_stat": 23.51}, "player_2": {"name": "Ravindra Jadeja", "player_stat": 29.94}, "stat": "average", "skill": "BOWL", "question_text": "Who has the better bowling average?", "greater": false}, {"player_1": {"name": "Amit Mishra", "player_stat": 3867.0}, "player_2": {"name": "Rahul Sharma", "player_stat": 1086.0}, "stat": "runs_given", "skill": "BOWL", "question_text": "Who has given away less runs?", "greater": false}, {"player_1": {"name": "Shane Warne", "player_stat": 25.38}, "player_2": {"name": "Munaf Patel", "player_stat": 22.94}, "stat": "average", "skill": "BOWL", "question_text": "Who has the better bowling average?", "greater": false}, {"player_1": {"name": "James Faulkner", "player_stat": 20.7}, "player_2": {"name": "Dhawal Kulkarni", "player_stat": 20.2}, "stat": "strike_rate", "skill": "BOWL", "question_text": "Who has the better bowling strike rate?", "greater": false}, {"player_1": {"name": "Bhuvneshwar Kumar", "player_stat": 8.0}, "player_2": {"name": "Rajat Bhatia", "player_stat": 1.0}, "stat": "maidens", "skill": "BOWL", "question_text": "Who has bowled more maidens?", "greater": true}, {"player_1": {"name": "Ishant Sharma", "player_stat": 71.0}, "player_2": {"name": "Daniel Vettori", "player_stat": 28.0}, "stat": "wickets", "skill": "BOWL", "question_text": "Who has taken more wickets?", "greater": true}, {"player_1": {"name": "Wayne Parnell", "player_stat": 26.0}, "player_2": {"name": "Mohammed Shami", "player_stat": 48.0}, "stat": "wickets", "skill": "BOWL", "question_text": "Who has taken more wickets?", "greater": true}, {"player_1": {"name": "Shaun Pollock", "player_stat": 1.0}, "player_2": {"name": "Rajat Bhatia", "player_stat": 1.0}, "stat": "maidens", "skill": "BOWL", "question_text": "Who has bowled more maidens?", "greater": true}, {"player_1": {"name": "Shadab Jakati", "player_stat": 23.0}, "player_2": {"name": "Kagiso Rabada", "player_stat": 12.9}, "stat": "strike_rate", "skill": "BOWL", "question_text": "Who has the better bowling strike rate?", "greater": false}, {"player_1": {"name": "Ravi Rampaul", "player_stat": 6.82}, "player_2": {"name": "Siddharth Trivedi", "player_stat": 7.58}, "stat": "economy", "skill": "BOWL", "question_text": "Who has the better economy rate?", "greater": false}, {"player_1": {"name": "Ashish Reddy", "player_stat": 0.0}, "player_2": {"name": "Mahela Jayawardene", "player_stat": 2.0}, "stat": "zeroes", "skill": "BAT", "question_text": "Who has more ducks?", "greater": true}, {"player_1": {"name": "David Miller", "player_stat": 33.63}, "player_2": {"name": "Steven Smith", "player_stat": 37.05}, "stat": "average", "skill": "BAT", "question_text": "Who has the better batting average?", "greater": true}, {"player_1": {"name": "Mohit Sharma", "player_stat": 26.84}, "player_2": {"name": "James Faulkner", "player_stat": 30.13}, "stat": "average", "skill": "BOWL", "question_text": "Who has the better bowling average?", "greater": false}, {"player_1": {"name": "David Miller", "player_stat": 33.63}, "player_2": {"name": "KL Rahul", "player_stat": 44.32}, "stat": "average", "skill": "BAT", "question_text": "Who has the better batting average?", "greater": true}]}