{"questions": [{"player_1": {"name": "Ramesh Powar", "player_stat": 40.53}, "player_2": {"name": "Anil Kumble", "player_stat": 23.51}, "stat": "average", "skill": "BOWL", "question_text": "Who has the lower bowling average?", "greater": false}, {"player_1": {"name": "Andre Russell", "player_stat": 8.0}, "player_2": {"name": "Michael Lumb", "player_stat": 1.0}, "stat": "fifties", "skill": "BAT", "question_text": "Who has scored more fifties?", "greater": true}, {"player_1": {"name": "Farveez Maharoof", "player_stat": 27.0}, "player_2": {"name": "Shadab Jakati", "player_stat": 47.0}, "stat": "wickets", "skill": "BOWL", "question_text": "Who has taken more wickets?", "greater": true}, {"player_1": {"name": "Michael Hussey", "player_stat": 122.64}, "player_2": {"name": "Jean-Paul Duminy", "player_stat": 124.02}, "stat": "strike_rate", "skill": "BAT", "question_text": "Who has the higher strike rate?", "greater": true}, {"player_1": {"name": "Mohammad Nabi", "player_stat": 322.0}, "player_2": {"name": "Dirk Nannes", "player_stat": 785.0}, "stat": "runs_given", "skill": "BOWL", "question_text": "Who has given away less runs?", "greater": false}, {"player_1": {"name": "Morne Morkel", "player_stat": 77.0}, "player_2": {"name": "Jofra Archer", "player_stat": 27.0}, "stat": "wickets", "skill": "BOWL", "question_text": "Who has taken more wickets?", "greater": true}, {"player_1": {"name": "Andre Russell", "player_stat": 98.0}, "player_2": {"name": "Sarfaraz Khan", "player_stat": 47.0}, "stat": "fours", "skill": "BAT", "question_text": "Who has hit more fours?", "greater": true}, {"player_1": {"name": "Shreyas Gopal", "player_stat": 21.0}, "player_2": {"name": "Sreenath Aravind", "player_stat": 23.08}, "stat": "average", "skill": "BOWL", "question_text": "Who has the lower bowling average?", "greater": false}, {"player_1": {"name": "Imran Tahir", "player_stat": 1611.0}, "player_2": {"name": "Roelof van der Merwe", "player_stat": 498.0}, "stat": "runs_given", "skill": "BOWL", "question_text": "Who has given away less runs?", "greater": false}, {"player_1": {"name": "Shane Warne", "player_stat": 7.27}, "player_2": {"name": "Krunal Pandya", "player_stat": 7.23}, "stat": "economy", "skill": "BOWL", "question_text": "Who has the lower economy rate?", "greater": false}, {"player_1": {"name": "Krunal Pandya", "player_stat": 1175.0}, "player_2": {"name": "Jean-Paul Duminy", "player_stat": 834.0}, "stat": "runs_given", "skill": "BOWL", "question_text": "Who has given away less runs?", "greater": false}, {"player_1": {"name": "Ali Murtaza", "player_stat": 9.0}, "player_2": {"name": "Kane Richardson", "player_stat": 18.0}, "stat": "wickets", "skill": "BOWL", "question_text": "Who has taken more wickets?", "greater": true}, {"player_1": {"name": "Azhar Mahmood", "player_stat": 7.82}, "player_2": {"name": "Umesh Yadav", "player_stat": 8.51}, "stat": "economy", "skill": "BOWL", "question_text": "Who has the lower economy rate?", "greater": false}, {"player_1": {"name": "Morne Morkel", "player_stat": 2089.0}, "player_2": {"name": "Pragyan Ojha", "player_stat": 2332.0}, "stat": "runs_given", "skill": "BOWL", "question_text": "Who has given away less runs?", "greater": false}, {"player_1": {"name": "Ravichandran Ashwin", "player_stat": 3311.0}, "player_2": {"name": "Iqbal Abdulla", "player_stat": 1109.0}, "stat": "runs_given", "skill": "BOWL", "question_text": "Who has given away less runs?", "greater": false}, {"player_1": {"name": "Martin Guptill", "player_stat": 1.0}, "player_2": {"name": "Suresh Raina", "player_stat": 8.0}, "stat": "zeroes", "skill": "BAT", "question_text": "Who has more ducks?", "greater": true}, {"player_1": {"name": "Lakshmipathy Balaji", "player_stat": 2.0}, "player_2": {"name": "Harbhajan Singh", "player_stat": 6.0}, "stat": "maidens", "skill": "BOWL", "question_text": "Who has bowled more maidens?", "greater": true}, {"player_1": {"name": "Ashok Dinda", "player_stat": 21.9}, "player_2": {"name": "Axar Patel", "player_stat": 24.1}, "stat": "strike_rate", "skill": "BOWL", "question_text": "Who has the lower bowling strike rate?", "greater": false}, {"player_1": {"name": "Harbhajan Singh", "player_stat": 64.0}, "player_2": {"name": "Thisara Perera", "player_stat": 40.0}, "stat": "highest", "skill": "BAT", "question_text": "Who has the greater highest score?", "greater": true}, {"player_1": {"name": "Amit Mishra", "player_stat": 7.33}, "player_2": {"name": "Mohit Sharma", "player_stat": 8.44}, "stat": "economy", "skill": "BOWL", "question_text": "Who has the lower economy rate?", "greater": false}]}