{"questions": [{"player_1": {"name": "Manish Pandey", "player_stat": 12.0}, "player_2": {"name": "Nitish Rana", "player_stat": 1.0}, "stat": "zeroes", "skill": "BAT", "question_text": "Who has more ducks?", "greater": true}, {"player_1": {"name": "Adam Gilchrist", "player_stat": 2.0}, "player_2": {"name": "Nitish Rana", "player_stat": 0.0}, "stat": "hundreds", "skill": "BAT", "question_text": "Who has scored more hundreds?", "greater": true}, {"player_1": {"name": "Rahul Tripathi", "player_stat": 26.46}, "player_2": {"name": "Steven Smith", "player_stat": 37.05}, "stat": "average", "skill": "BAT", "question_text": "Who has the better batting average?", "greater": true}, {"player_1": {"name": "Shakib Al Hasan", "player_stat": 1.0}, "player_2": {"name": "Yuvraj Singh", "player_stat": 0.0}, "stat": "maidens", "skill": "BOWL", "question_text": "Who has bowled more maidens?", "greater": true}, {"player_1": {"name": "Brett Lee", "player_stat": 3.0}, "player_2": {"name": "Mitchell Marsh", "player_stat": 0.0}, "stat": "maidens", "skill": "BOWL", "question_text": "Who has bowled more maidens?", "greater": true}, {"player_1": {"name": "Brett Lee", "player_stat": 1095.0}, "player_2": {"name": "Dhawal Kulkarni", "player_stat": 2404.0}, "stat": "runs_given", "skill": "BOWL", "question_text": "Who has given away less runs?", "greater": false}, {"player_1": {"name": "S Badrinath", "player_stat": 6.0}, "player_2": {"name": "Yusuf Pathan", "player_stat": 9.0}, "stat": "zeroes", "skill": "BAT", "question_text": "Who has more ducks?", "greater": true}, {"player_1": {"name": "Amit Mishra", "player_stat": 6.0}, "player_2": {"name": "Lasith Malinga", "player_stat": 8.0}, "stat": "maidens", "skill": "BOWL", "question_text": "Who has bowled more maidens?", "greater": true}, {"player_1": {"name": "Ambati Rayudu", "player_stat": 100.0}, "player_2": {"name": "Harbhajan Singh", "player_stat": 64.0}, "stat": "highest", "skill": "BAT", "question_text": "Who has the greater highest score?", "greater": true}, {"player_1": {"name": "Axar Patel", "player_stat": 73.0}, "player_2": {"name": "Doug Bollinger", "player_stat": 37.0}, "stat": "wickets", "skill": "BOWL", "question_text": "Who has taken more wickets?", "greater": true}, {"player_1": {"name": "Harbhajan Singh", "player_stat": 6.0}, "player_2": {"name": "Ashish Reddy", "player_stat": 0.0}, "stat": "maidens", "skill": "BOWL", "question_text": "Who has bowled more maidens?", "greater": true}, {"player_1": {"name": "Vijay Shankar", "player_stat": 133.57}, "player_2": {"name": "AB de Villiers", "player_stat": 151.97}, "stat": "strike_rate", "skill": "BAT", "question_text": "Who has the better batting strike rate?", "greater": true}, {"player_1": {"name": "Dimitri Mascarenhas", "player_stat": 1.0}, "player_2": {"name": "Dale Steyn", "player_stat": 7.0}, "stat": "maidens", "skill": "BOWL", "question_text": "Who has bowled more maidens?", "greater": true}, {"player_1": {"name": "Chris Morris", "player_stat": 2.0}, "player_2": {"name": "MS Dhoni", "player_stat": 23.0}, "stat": "fifties", "skill": "BAT", "question_text": "Who has scored more fifties?", "greater": true}, {"player_1": {"name": "Shane Warne", "player_stat": 1.0}, "player_2": {"name": "Farveez Maharoof", "player_stat": 0.0}, "stat": "maidens", "skill": "BOWL", "question_text": "Who has bowled more maidens?", "greater": true}, {"player_1": {"name": "Gautam Gambhir", "player_stat": 0.0}, "player_2": {"name": "Faf du Plessis", "player_stat": 0.0}, "stat": "hundreds", "skill": "BAT", "question_text": "Who has scored more hundreds?", "greater": true}, {"player_1": {"name": "Ambati Rayudu", "player_stat": 19.0}, "player_2": {"name": "Ryan ten Doeschate", "player_stat": 1.0}, "stat": "fifties", "skill": "BAT", "question_text": "Who has scored more fifties?", "greater": true}, {"player_1": {"name": "Azhar Mahmood", "player_stat": 18.5}, "player_2": {"name": "Iqbal Abdulla", "player_stat": 23.0}, "stat": "strike_rate", "skill": "BOWL", "question_text": "Who has the better bowling strike rate?", "greater": false}, {"player_1": {"name": "Johan Botha", "player_stat": 32.0}, "player_2": {"name": "Shreyas Gopal", "player_stat": 22.22}, "stat": "average", "skill": "BOWL", "question_text": "Who has the better bowling average?", "greater": false}, {"player_1": {"name": "Travis Head", "player_stat": 138.51}, "player_2": {"name": "Chris Lynn", "player_stat": 140.65}, "stat": "strike_rate", "skill": "BAT", "question_text": "Who has the better batting strike rate?", "greater": true}]}