{"questions": [{"player_1": {"name": "Rishabh Pant", "player_stat": 4.0}, "player_2": {"name": "James Hopes", "player_stat": 1.0}, "stat": "zeroes", "skill": "BAT", "question_text": "Who has more ducks?", "greater": true}, {"player_1": {"name": "Rashid Khan", "player_stat": 1297.0}, "player_2": {"name": "Muttiah Muralitharan", "player_stat": 1696.0}, "stat": "runs_given", "skill": "BOWL", "question_text": "Who has given away less runs?", "greater": false}, {"player_1": {"name": "Mohit Sharma", "player_stat": 8.44}, "player_2": {"name": "Axar Patel", "player_stat": 7.32}, "stat": "economy", "skill": "BOWL", "question_text": "Who has the better economy rate?", "greater": false}, {"player_1": {"name": "Jacques Kallis", "player_stat": 65.0}, "player_2": {"name": "Chris Morris", "player_stat": 69.0}, "stat": "wickets", "skill": "BOWL", "question_text": "Who has taken more wickets?", "greater": true}, {"player_1": {"name": "Glenn McGrath", "player_stat": 29.75}, "player_2": {"name": "Brad Hogg", "player_stat": 24.78}, "stat": "average", "skill": "BOWL", "question_text": "Who has the better bowling average?", "greater": false}, {"player_1": {"name": "Jofra Archer", "player_stat": 31.0}, "player_2": {"name": "Dimitri Mascarenhas", "player_stat": 19.0}, "stat": "wickets", "skill": "BOWL", "question_text": "Who has taken more wickets?", "greater": true}, {"player_1": {"name": "Praveen Kumar", "player_stat": 7.72}, "player_2": {"name": "Mohammed Shami", "player_stat": 8.91}, "stat": "economy", "skill": "BOWL", "question_text": "Who has the better economy rate?", "greater": false}, {"player_1": {"name": "Glenn Maxwell", "player_stat": 0.0}, "player_2": {"name": "Kane Williamson", "player_stat": 0.0}, "stat": "hundreds", "skill": "BAT", "question_text": "Who has scored more hundreds?", "greater": true}, {"player_1": {"name": "Lendl Simmons", "player_stat": 109.0}, "player_2": {"name": "Kane Williamson", "player_stat": 116.0}, "stat": "fours", "skill": "BAT", "question_text": "Who has hit more fours?", "greater": true}, {"player_1": {"name": "Lasith Malinga", "player_stat": 3366.0}, "player_2": {"name": "Rajat Bhatia", "player_stat": 2020.0}, "stat": "runs_given", "skill": "BOWL", "question_text": "Who has given away less runs?", "greater": false}, {"player_1": {"name": "Roelof van der Merwe", "player_stat": 23.71}, "player_2": {"name": "Brad Hogg", "player_stat": 24.78}, "stat": "average", "skill": "BOWL", "question_text": "Who has the better bowling average?", "greater": false}, {"player_1": {"name": "Axar Patel", "player_stat": 2193.0}, "player_2": {"name": "Ashish Reddy", "player_stat": 396.0}, "stat": "runs_given", "skill": "BOWL", "question_text": "Who has given away less runs?", "greater": false}, {"player_1": {"name": "Shaun Pollock", "player_stat": 301.0}, "player_2": {"name": "RP Singh", "player_stat": 2338.0}, "stat": "runs_given", "skill": "BOWL", "question_text": "Who has given away less runs?", "greater": false}, {"player_1": {"name": "S Badrinath", "player_stat": 0.0}, "player_2": {"name": "Moeen Ali", "player_stat": 0.0}, "stat": "hundreds", "skill": "BAT", "question_text": "Who has scored more hundreds?", "greater": true}, {"player_1": {"name": "Shane Watson", "player_stat": 7.93}, "player_2": {"name": "Chris Morris", "player_stat": 7.98}, "stat": "economy", "skill": "BOWL", "question_text": "Who has the better economy rate?", "greater": false}, {"player_1": {"name": "Michael Lumb", "player_stat": 45.0}, "player_2": {"name": "Gautam Gambhir", "player_stat": 492.0}, "stat": "fours", "skill": "BAT", "question_text": "Who has hit more fours?", "greater": true}, {"player_1": {"name": "Bhuvneshwar Kumar", "player_stat": 136.0}, "player_2": {"name": "Johan Botha", "player_stat": 25.0}, "stat": "wickets", "skill": "BOWL", "question_text": "Who has taken more wickets?", "greater": true}, {"player_1": {"name": "Andre Russell", "player_stat": 99.0}, "player_2": {"name": "Moeen Ali", "player_stat": 21.0}, "stat": "fours", "skill": "BAT", "question_text": "Who has hit more fours?", "greater": true}, {"player_1": {"name": "Wayne Parnell", "player_stat": 7.35}, "player_2": {"name": "Siddarth Kaul", "player_stat": 8.65}, "stat": "economy", "skill": "BOWL", "question_text": "Who has the better economy rate?", "greater": false}, {"player_1": {"name": "Ben Hilfenhaus", "player_stat": 479.0}, "player_2": {"name": "RP Singh", "player_stat": 2338.0}, "stat": "runs_given", "skill": "BOWL", "question_text": "Who has given away less runs?", "greater": false}]}