{"questions": [{"player_1": {"name": "Jofra Archer", "player_stat": 24.45}, "player_2": {"name": "Muttiah Muralitharan", "player_stat": 26.92}, "stat": "average", "skill": "BOWL", "question_text": "Who has the better bowling average?", "greater": false}, {"player_1": {"name": "Ishant Sharma", "player_stat": 36.67}, "player_2": {"name": "Krunal Pandya", "player_stat": 29.81}, "stat": "average", "skill": "BOWL", "question_text": "Who has the better bowling average?", "greater": false}, {"player_1": {"name": "Kieron Pollard", "player_stat": 8.84}, "player_2": {"name": "Amit Mishra", "player_stat": 7.34}, "stat": "economy", "skill": "BOWL", "question_text": "Who has the better economy rate?", "greater": false}, {"player_1": {"name": "Shakib Al Hasan", "player_stat": 59.0}, "player_2": {"name": "Siddarth Kaul", "player_stat": 51.0}, "stat": "wickets", "skill": "BOWL", "question_text": "Who has taken more wickets?", "greater": true}, {"player_1": {"name": "Ryan ten Doeschate", "player_stat": 1.0}, "player_2": {"name": "Chris Lynn", "player_stat": 10.0}, "stat": "fifties", "skill": "BAT", "question_text": "Who has scored more fifties?", "greater": true}, {"player_1": {"name": "Shakib Al Hasan", "player_stat": 22.5}, "player_2": {"name": "Dwayne Bravo", "player_stat": 17.9}, "stat": "strike_rate", "skill": "BOWL", "question_text": "Who has the better bowling strike rate?", "greater": false}, {"player_1": {"name": "Azhar Mahmood", "player_stat": 24.13}, "player_2": {"name": "Jacques Kallis", "player_stat": 35.27}, "stat": "average", "skill": "BOWL", "question_text": "Who has the better bowling average?", "greater": false}, {"player_1": {"name": "Shreyas Gopal", "player_stat": 1.0}, "player_2": {"name": "Andre Russell", "player_stat": 0.0}, "stat": "maidens", "skill": "BOWL", "question_text": "Who has bowled more maidens?", "greater": true}, {"player_1": {"name": "KL Rahul", "player_stat": 44.68}, "player_2": {"name": "Glenn Maxwell", "player_stat": 22.46}, "stat": "average", "skill": "BAT", "question_text": "Who has the better batting average?", "greater": true}, {"player_1": {"name": "Suryakumar Yadav", "player_stat": 28.73}, "player_2": {"name": "Martin Guptill", "player_stat": 22.5}, "stat": "average", "skill": "BAT", "question_text": "Who has the better batting average?", "greater": true}, {"player_1": {"name": "Karn Sharma", "player_stat": 1.0}, "player_2": {"name": "Rahul Tewatia", "player_stat": 0.0}, "stat": "maidens", "skill": "BOWL", "question_text": "Who has bowled more maidens?", "greater": true}, {"player_1": {"name": "Mitchell Johnson", "player_stat": 20.1}, "player_2": {"name": "Morne Morkel", "player_stat": 21.1}, "stat": "strike_rate", "skill": "BOWL", "question_text": "Who has the better bowling strike rate?", "greater": false}, {"player_1": {"name": "RP Singh", "player_stat": 7.9}, "player_2": {"name": "Vinay Kumar", "player_stat": 8.39}, "stat": "economy", "skill": "BOWL", "question_text": "Who has the better economy rate?", "greater": false}, {"player_1": {"name": "Murali Kartik", "player_stat": 37.0}, "player_2": {"name": "Rahul Chahar", "player_stat": 20.1}, "stat": "strike_rate", "skill": "BOWL", "question_text": "Who has the better bowling strike rate?", "greater": false}, {"player_1": {"name": "Karn Sharma", "player_stat": 1445.0}, "player_2": {"name": "Washington Sundar", "player_stat": 523.0}, "stat": "runs_given", "skill": "BOWL", "question_text": "Who has given away less runs?", "greater": false}, {"player_1": {"name": "Ryan ten Doeschate", "player_stat": 70.0}, "player_2": {"name": "Krunal Pandya", "player_stat": 86.0}, "stat": "highest", "skill": "BAT", "question_text": "Who has the greater highest score?", "greater": true}, {"player_1": {"name": "David Wiese", "player_stat": 402.0}, "player_2": {"name": "Ankit Sharma", "player_stat": 450.0}, "stat": "runs_given", "skill": "BOWL", "question_text": "Who has given away less runs?", "greater": false}, {"player_1": {"name": "Shaun Pollock", "player_stat": 27.36}, "player_2": {"name": "Shane Watson", "player_stat": 29.15}, "stat": "average", "skill": "BOWL", "question_text": "Who has the better bowling average?", "greater": false}, {"player_1": {"name": "Zaheer Khan", "player_stat": 21.5}, "player_2": {"name": "Brad Hogg", "player_stat": 19.9}, "stat": "strike_rate", "skill": "BOWL", "question_text": "Who has the better bowling strike rate?", "greater": false}, {"player_1": {"name": "Kevon Cooper", "player_stat": 22.93}, "player_2": {"name": "Dhawal Kulkarni", "player_stat": 27.95}, "stat": "average", "skill": "BOWL", "question_text": "Who has the better bowling average?", "greater": false}]}