{"questions": [{"player_1": {"name": "Mitchell Starc", "player_stat": 7.16}, "player_2": {"name": "Kevon Cooper", "player_stat": 7.88}, "stat": "economy", "skill": "BOWL", "question_text": "Who has the better economy rate?", "greater": false}, {"player_1": {"name": "Rashid Khan", "player_stat": 3.0}, "player_2": {"name": "Rahul Sharma", "player_stat": 1.0}, "stat": "maidens", "skill": "BOWL", "question_text": "Who has bowled more maidens?", "greater": true}, {"player_1": {"name": "James Franklin", "player_stat": 0.0}, "player_2": {"name": "Michael Lumb", "player_stat": 0.0}, "stat": "hundreds", "skill": "BAT", "question_text": "Who has scored more hundreds?", "greater": true}, {"player_1": {"name": "Khaleel Ahmed", "player_stat": 8.83}, "player_2": {"name": "Kagiso Rabada", "player_stat": 8.08}, "stat": "economy", "skill": "BOWL", "question_text": "Who has the better economy rate?", "greater": false}, {"player_1": {"name": "Andre Russell", "player_stat": 0.0}, "player_2": {"name": "Nicholas Pooran", "player_stat": 0.0}, "stat": "hundreds", "skill": "BAT", "question_text": "Who has scored more hundreds?", "greater": true}, {"player_1": {"name": "Ishant Sharma", "player_stat": 36.67}, "player_2": {"name": "Lasith Malinga", "player_stat": 19.8}, "stat": "average", "skill": "BOWL", "question_text": "Who has the better bowling average?", "greater": false}, {"player_1": {"name": "Sarfaraz Khan", "player_stat": 11.0}, "player_2": {"name": "Travis Head", "player_stat": 8.0}, "stat": "sixes", "skill": "BAT", "question_text": "Who has hit more sixes?", "greater": true}, {"player_1": {"name": "Sanath Jayasuriya", "player_stat": 39.0}, "player_2": {"name": "Ben Rohrer", "player_stat": 5.0}, "stat": "sixes", "skill": "BAT", "question_text": "Who has hit more sixes?", "greater": true}, {"player_1": {"name": "Lakshmipathy Balaji", "player_stat": 8.04}, "player_2": {"name": "Brad Hogg", "player_stat": 7.46}, "stat": "economy", "skill": "BOWL", "question_text": "Who has the better economy rate?", "greater": false}, {"player_1": {"name": "Ben Hilfenhaus", "player_stat": 22.0}, "player_2": {"name": "Ashok Dinda", "player_stat": 69.0}, "stat": "wickets", "skill": "BOWL", "question_text": "Who has taken more wickets?", "greater": true}, {"player_1": {"name": "Virender Sehwag", "player_stat": 122.0}, "player_2": {"name": "Quinton de Kock", "player_stat": 108.0}, "stat": "highest", "skill": "BAT", "question_text": "Who has the greater highest score?", "greater": true}, {"player_1": {"name": "Ravichandran Ashwin", "player_stat": 26.27}, "player_2": {"name": "Mustafizur Rahman", "player_stat": 28.54}, "stat": "average", "skill": "BOWL", "question_text": "Who has the better bowling average?", "greater": false}, {"player_1": {"name": "Doug Bollinger", "player_stat": 18.72}, "player_2": {"name": "Siddharth Trivedi", "player_stat": 29.29}, "stat": "average", "skill": "BOWL", "question_text": "Who has the better bowling average?", "greater": false}, {"player_1": {"name": "Shane Warne", "player_stat": 7.27}, "player_2": {"name": "Kieron Pollard", "player_stat": 8.85}, "stat": "economy", "skill": "BOWL", "question_text": "Who has the better economy rate?", "greater": false}, {"player_1": {"name": "Ben Cutting", "player_stat": 21.63}, "player_2": {"name": "Jos Buttler", "player_stat": 34.11}, "stat": "average", "skill": "BAT", "question_text": "Who has the better batting average?", "greater": true}, {"player_1": {"name": "Krunal Pandya", "player_stat": 7.23}, "player_2": {"name": "Shane Watson", "player_stat": 7.93}, "stat": "economy", "skill": "BOWL", "question_text": "Who has the better economy rate?", "greater": false}, {"player_1": {"name": "Karn Sharma", "player_stat": 1445.0}, "player_2": {"name": "Kagiso Rabada", "player_stat": 682.0}, "stat": "runs_given", "skill": "BOWL", "question_text": "Who has given away less runs?", "greater": false}, {"player_1": {"name": "Harbhajan Singh", "player_stat": 6.0}, "player_2": {"name": "Brad Hogg", "player_stat": 1.0}, "stat": "maidens", "skill": "BOWL", "question_text": "Who has bowled more maidens?", "greater": true}, {"player_1": {"name": "Virender Sehwag", "player_stat": 334.0}, "player_2": {"name": "Mahela Jayawardene", "player_stat": 200.0}, "stat": "fours", "skill": "BAT", "question_text": "Who has hit more fours?", "greater": true}, {"player_1": {"name": "Colin de Grandhomme", "player_stat": 18.0}, "player_2": {"name": "Sachin Tendulkar", "player_stat": 29.0}, "stat": "sixes", "skill": "BAT", "question_text": "Who has hit more sixes?", "greater": true}]}