{"questions": [{"player_1": {"name": "Chris Lynn", "player_stat": 93.0}, "player_2": {"name": "KL Rahul", "player_stat": 132.0}, "stat": "highest", "skill": "BAT", "question_text": "Who has the greater highest score?", "greater": true}, {"player_1": {"name": "Ashish Reddy", "player_stat": 9.06}, "player_2": {"name": "Zaheer Khan", "player_stat": 7.58}, "stat": "economy", "skill": "BOWL", "question_text": "Who has the better economy rate?", "greater": false}, {"player_1": {"name": "Dale Steyn", "player_stat": 22.1}, "player_2": {"name": "Rashid Khan", "player_stat": 20.2}, "stat": "strike_rate", "skill": "BOWL", "question_text": "Who has the better bowling strike rate?", "greater": false}, {"player_1": {"name": "Wayne Parnell", "player_stat": 26.96}, "player_2": {"name": "Anil Kumble", "player_stat": 23.51}, "stat": "average", "skill": "BOWL", "question_text": "Who has the better bowling average?", "greater": false}, {"player_1": {"name": "James Faulkner", "player_stat": 135.47}, "player_2": {"name": "AB de Villiers", "player_stat": 151.97}, "stat": "strike_rate", "skill": "BAT", "question_text": "Who has the better batting strike rate?", "greater": true}, {"player_1": {"name": "Jaydev Unadkat", "player_stat": 20.2}, "player_2": {"name": "Jean-Paul Duminy", "player_stat": 29.4}, "stat": "strike_rate", "skill": "BOWL", "question_text": "Who has the better bowling strike rate?", "greater": false}, {"player_1": {"name": "Moeen Ali", "player_stat": 21.0}, "player_2": {"name": "Albie Morkel", "player_stat": 61.0}, "stat": "fours", "skill": "BAT", "question_text": "Who has hit more fours?", "greater": true}, {"player_1": {"name": "Samuel Badree", "player_stat": 7.41}, "player_2": {"name": "Siddarth Kaul", "player_stat": 8.65}, "stat": "economy", "skill": "BOWL", "question_text": "Who has the better economy rate?", "greater": false}, {"player_1": {"name": "Ryan Harris", "player_stat": 3.0}, "player_2": {"name": "Jasprit Bumrah", "player_stat": 4.0}, "stat": "maidens", "skill": "BOWL", "question_text": "Who has bowled more maidens?", "greater": true}, {"player_1": {"name": "Bhuvneshwar Kumar", "player_stat": 7.23}, "player_2": {"name": "Parvinder Awana", "player_stat": 8.26}, "stat": "economy", "skill": "BOWL", "question_text": "Who has the better economy rate?", "greater": false}, {"player_1": {"name": "RP Singh", "player_stat": 7.9}, "player_2": {"name": "Ben Hilfenhaus", "player_stat": 7.72}, "stat": "economy", "skill": "BOWL", "question_text": "Who has the better economy rate?", "greater": false}, {"player_1": {"name": "MS Dhoni", "player_stat": 23.0}, "player_2": {"name": "Shane Watson", "player_stat": 20.0}, "stat": "fifties", "skill": "BAT", "question_text": "Who has scored more fifties?", "greater": true}, {"player_1": {"name": "Dwayne Smith", "player_stat": 28.39}, "player_2": {"name": "Hashim Amla", "player_stat": 44.38}, "stat": "average", "skill": "BAT", "question_text": "Who has the better batting average?", "greater": true}, {"player_1": {"name": "Ravi Bopara", "player_stat": 117.21}, "player_2": {"name": "Sanath Jayasuriya", "player_stat": 144.36}, "stat": "strike_rate", "skill": "BAT", "question_text": "Who has the better batting strike rate?", "greater": true}, {"player_1": {"name": "Dhawal Kulkarni", "player_stat": 27.95}, "player_2": {"name": "Dale Steyn", "player_stat": 25.41}, "stat": "average", "skill": "BOWL", "question_text": "Who has the better bowling average?", "greater": false}, {"player_1": {"name": "Wayne Parnell", "player_stat": 7.35}, "player_2": {"name": "Sreenath Aravind", "player_stat": 8.2}, "stat": "economy", "skill": "BOWL", "question_text": "Who has the better economy rate?", "greater": false}, {"player_1": {"name": "Mitchell Marsh", "player_stat": 15.9}, "player_2": {"name": "Jofra Archer", "player_stat": 19.7}, "stat": "strike_rate", "skill": "BOWL", "question_text": "Who has the better bowling strike rate?", "greater": false}, {"player_1": {"name": "MS Dhoni", "player_stat": 137.81}, "player_2": {"name": "Jos Buttler", "player_stat": 150.6}, "stat": "strike_rate", "skill": "BAT", "question_text": "Who has the better batting strike rate?", "greater": true}, {"player_1": {"name": "Nathan Coulter-Nile", "player_stat": 36.0}, "player_2": {"name": "Siddarth Kaul", "player_stat": 51.0}, "stat": "wickets", "skill": "BOWL", "question_text": "Who has taken more wickets?", "greater": true}, {"player_1": {"name": "S Badrinath", "player_stat": 11.0}, "player_2": {"name": "Chris Morris", "player_stat": 2.0}, "stat": "fifties", "skill": "BAT", "question_text": "Who has scored more fifties?", "greater": true}]}