{"questions": [{"player_1": {"name": "Ben Rohrer", "player_stat": 5.0}, "player_2": {"name": "David Warner", "player_stat": 184.0}, "stat": "sixes", "skill": "BAT", "question_text": "Who has hit more sixes?", "greater": true}, {"player_1": {"name": "Kane Williamson", "player_stat": 134.79}, "player_2": {"name": "Moeen Ali", "player_stat": 165.92}, "stat": "strike_rate", "skill": "BAT", "question_text": "Who has the higher strike rate?", "greater": true}, {"player_1": {"name": "Iqbal Abdulla", "player_stat": 104.76}, "player_2": {"name": "Rishabh Pant", "player_stat": 160.51}, "stat": "strike_rate", "skill": "BAT", "question_text": "Who has the higher strike rate?", "greater": true}, {"player_1": {"name": "Mitchell McClenaghan", "player_stat": 25.39}, "player_2": {"name": "Dwayne Bravo", "player_stat": 24.8}, "stat": "average", "skill": "BOWL", "question_text": "Who has the better bowling average?", "greater": false}, {"player_1": {"name": "Mohit Sharma", "player_stat": 19.0}, "player_2": {"name": "Kevon Cooper", "player_stat": 17.4}, "stat": "strike_rate", "skill": "BOWL", "question_text": "Who has the lower bowling strike rate?", "greater": false}, {"player_1": {"name": "Jasprit Bumrah", "player_stat": 4.0}, "player_2": {"name": "Ankit Sharma", "player_stat": 0.0}, "stat": "maidens", "skill": "BOWL", "question_text": "Who has bowled more maidens?", "greater": true}, {"player_1": {"name": "James Hopes", "player_stat": 1.0}, "player_2": {"name": "Chris Lynn", "player_stat": 3.0}, "stat": "zeroes", "skill": "BAT", "question_text": "Who has more ducks?", "greater": true}, {"player_1": {"name": "Johan Botha", "player_stat": 25.0}, "player_2": {"name": "Daniel Vettori", "player_stat": 28.0}, "stat": "wickets", "skill": "BOWL", "question_text": "Who has taken more wickets?", "greater": true}, {"player_1": {"name": "Thisara Perera", "player_stat": 19.18}, "player_2": {"name": "Andrew Symonds", "player_stat": 36.07}, "stat": "average", "skill": "BAT", "question_text": "Who has the better batting average?", "greater": true}, {"player_1": {"name": "Wayne Parnell", "player_stat": 701.0}, "player_2": {"name": "Praveen Kumar", "player_stat": 3251.0}, "stat": "runs_given", "skill": "BOWL", "question_text": "Who has given away less runs?", "greater": false}, {"player_1": {"name": "Shaun Pollock", "player_stat": 25.0}, "player_2": {"name": "Doug Bollinger", "player_stat": 15.5}, "stat": "strike_rate", "skill": "BOWL", "question_text": "Who has the lower bowling strike rate?", "greater": false}, {"player_1": {"name": "Azhar Mahmood", "player_stat": 0.0}, "player_2": {"name": "Amit Mishra", "player_stat": 6.0}, "stat": "maidens", "skill": "BOWL", "question_text": "Who has bowled more maidens?", "greater": true}, {"player_1": {"name": "Jean-Paul Duminy", "player_stat": 23.0}, "player_2": {"name": "Ashish Reddy", "player_stat": 18.0}, "stat": "wickets", "skill": "BOWL", "question_text": "Who has taken more wickets?", "greater": true}, {"player_1": {"name": "Manoj Tiwary", "player_stat": 0.0}, "player_2": {"name": "David Warner", "player_stat": 4.0}, "stat": "hundreds", "skill": "BAT", "question_text": "Who has scored more hundreds?", "greater": true}, {"player_1": {"name": "Brad Hodge", "player_stat": 0.0}, "player_2": {"name": "Manish Pandey", "player_stat": 1.0}, "stat": "hundreds", "skill": "BAT", "question_text": "Who has scored more hundreds?", "greater": true}, {"player_1": {"name": "Dimitri Mascarenhas", "player_stat": 18.73}, "player_2": {"name": "Ryan Harris", "player_stat": 23.26}, "stat": "average", "skill": "BOWL", "question_text": "Who has the better bowling average?", "greater": false}, {"player_1": {"name": "Hashim Amla", "player_stat": 2.0}, "player_2": {"name": "Albie Morkel", "player_stat": 0.0}, "stat": "hundreds", "skill": "BAT", "question_text": "Who has scored more hundreds?", "greater": true}, {"player_1": {"name": "Jacques Kallis", "player_stat": 7.89}, "player_2": {"name": "Imran Tahir", "player_stat": 7.88}, "stat": "economy", "skill": "BOWL", "question_text": "Who has the lower economy rate?", "greater": false}, {"player_1": {"name": "Faf du Plessis", "player_stat": 128.24}, "player_2": {"name": "Ben Cutting", "player_stat": 168.79}, "stat": "strike_rate", "skill": "BAT", "question_text": "Who has the higher strike rate?", "greater": true}, {"player_1": {"name": "Ishant Sharma", "player_stat": 4.0}, "player_2": {"name": "Muttiah Muralitharan", "player_stat": 1.0}, "stat": "maidens", "skill": "BOWL", "question_text": "Who has bowled more maidens?", "greater": true}]}