{"questions": [{"player_1": {"name": "Lakshmipathy Balaji", "player_stat": 76.0}, "player_2": {"name": "Irfan Pathan", "player_stat": 80.0}, "stat": "wickets", "skill": "BOWL", "question_text": "Who has taken more wickets?", "greater": true}, {"player_1": {"name": "Kieron Pollard", "player_stat": 21.6}, "player_2": {"name": "Amit Mishra", "player_stat": 19.7}, "stat": "strike_rate", "skill": "BOWL", "question_text": "Who has the better bowling strike rate?", "greater": false}, {"player_1": {"name": "Mohammad Nabi", "player_stat": 0.0}, "player_2": {"name": "Ravichandran Ashwin", "player_stat": 4.0}, "stat": "maidens", "skill": "BOWL", "question_text": "Who has bowled more maidens?", "greater": true}, {"player_1": {"name": "Nathan Coulter-Nile", "player_stat": 19.97}, "player_2": {"name": "Murali Kartik", "player_stat": 44.77}, "stat": "average", "skill": "BOWL", "question_text": "Who has the better bowling average?", "greater": false}, {"player_1": {"name": "Bhuvneshwar Kumar", "player_stat": 8.0}, "player_2": {"name": "Anil Kumble", "player_stat": 1.0}, "stat": "maidens", "skill": "BOWL", "question_text": "Who has bowled more maidens?", "greater": true}, {"player_1": {"name": "Jean-Paul Duminy", "player_stat": 124.02}, "player_2": {"name": "Krunal Pandya", "player_stat": 145.52}, "stat": "strike_rate", "skill": "BAT", "question_text": "Who has the better batting strike rate?", "greater": true}, {"player_1": {"name": "Glenn Maxwell", "player_stat": 9.0}, "player_2": {"name": "Gautam Gambhir", "player_stat": 12.0}, "stat": "zeroes", "skill": "BAT", "question_text": "Who has more ducks?", "greater": true}, {"player_1": {"name": "Ben Hilfenhaus", "player_stat": 16.9}, "player_2": {"name": "Andre Russell", "player_stat": 18.4}, "stat": "strike_rate", "skill": "BOWL", "question_text": "Who has the better bowling strike rate?", "greater": false}, {"player_1": {"name": "Sunil Narine", "player_stat": 163.19}, "player_2": {"name": "KL Rahul", "player_stat": 138.62}, "stat": "strike_rate", "skill": "BAT", "question_text": "Who has the better batting strike rate?", "greater": true}, {"player_1": {"name": "Ravi Bopara", "player_stat": 0.0}, "player_2": {"name": "Iqbal Abdulla", "player_stat": 0.0}, "stat": "hundreds", "skill": "BAT", "question_text": "Who has scored more hundreds?", "greater": true}, {"player_1": {"name": "Rahul Chahar", "player_stat": 7.09}, "player_2": {"name": "Rahul Tewatia", "player_stat": 7.45}, "stat": "economy", "skill": "BOWL", "question_text": "Who has the better economy rate?", "greater": false}, {"player_1": {"name": "Ravi Rampaul", "player_stat": 21.28}, "player_2": {"name": "Muttiah Muralitharan", "player_stat": 26.92}, "stat": "average", "skill": "BOWL", "question_text": "Who has the better bowling average?", "greater": false}, {"player_1": {"name": "Rajat Bhatia", "player_stat": 7.4}, "player_2": {"name": "Muttiah Muralitharan", "player_stat": 6.67}, "stat": "economy", "skill": "BOWL", "question_text": "Who has the better economy rate?", "greater": false}, {"player_1": {"name": "Steven Smith", "player_stat": 36.52}, "player_2": {"name": "Quinton de Kock", "player_stat": 29.51}, "stat": "average", "skill": "BAT", "question_text": "Who has the better batting average?", "greater": true}, {"player_1": {"name": "Jofra Archer", "player_stat": 24.45}, "player_2": {"name": "Zaheer Khan", "player_stat": 27.27}, "stat": "average", "skill": "BOWL", "question_text": "Who has the better bowling average?", "greater": false}, {"player_1": {"name": "Dirk Nannes", "player_stat": 28.0}, "player_2": {"name": "Khaleel Ahmed", "player_stat": 21.0}, "stat": "wickets", "skill": "BOWL", "question_text": "Who has taken more wickets?", "greater": true}, {"player_1": {"name": "Brad Hodge", "player_stat": 6.0}, "player_2": {"name": "Suryakumar Yadav", "player_stat": 8.0}, "stat": "fifties", "skill": "BAT", "question_text": "Who has scored more fifties?", "greater": true}, {"player_1": {"name": "Dirk Nannes", "player_stat": 28.0}, "player_2": {"name": "Harbhajan Singh", "player_stat": 150.0}, "stat": "wickets", "skill": "BOWL", "question_text": "Who has taken more wickets?", "greater": true}, {"player_1": {"name": "Praveen Kumar", "player_stat": 7.72}, "player_2": {"name": "Rahul Tewatia", "player_stat": 7.45}, "stat": "economy", "skill": "BOWL", "question_text": "Who has the better economy rate?", "greater": false}, {"player_1": {"name": "Glenn Maxwell", "player_stat": 157.84}, "player_2": {"name": "Ashish Reddy", "player_stat": 145.07}, "stat": "strike_rate", "skill": "BAT", "question_text": "Who has the better batting strike rate?", "greater": true}]}