{"questions": [{"player_1": {"name": "Lendl Simmons", "player_stat": 11.0}, "player_2": {"name": "Sarfaraz Khan", "player_stat": 1.0}, "stat": "fifties", "skill": "BAT", "question_text": "Who has scored more fifties?", "greater": true}, {"player_1": {"name": "James Hopes", "player_stat": 49.0}, "player_2": {"name": "Hashim Amla", "player_stat": 60.0}, "stat": "fours", "skill": "BAT", "question_text": "Who has hit more fours?", "greater": true}, {"player_1": {"name": "Nicholas Pooran", "player_stat": 0.0}, "player_2": {"name": "Andrew Symonds", "player_stat": 1.0}, "stat": "hundreds", "skill": "BAT", "question_text": "Who has scored more hundreds?", "greater": true}, {"player_1": {"name": "Jacques Kallis", "player_stat": 65.0}, "player_2": {"name": "Rahul Sharma", "player_stat": 40.0}, "stat": "wickets", "skill": "BOWL", "question_text": "Who has taken more wickets?", "greater": true}, {"player_1": {"name": "Shreyas Gopal", "player_stat": 21.0}, "player_2": {"name": "Mitchell Johnson", "player_stat": 27.9}, "stat": "average", "skill": "BOWL", "question_text": "Who has the lower bowling average?", "greater": false}, {"player_1": {"name": "Ben Hilfenhaus", "player_stat": 479.0}, "player_2": {"name": "Jasprit Bumrah", "player_stat": 2257.0}, "stat": "runs_given", "skill": "BOWL", "question_text": "Who has given away less runs?", "greater": false}, {"player_1": {"name": "Andrew Symonds", "player_stat": 5.0}, "player_2": {"name": "Suresh Raina", "player_stat": 38.0}, "stat": "fifties", "skill": "BAT", "question_text": "Who has scored more fifties?", "greater": true}, {"player_1": {"name": "Sanju Samson", "player_stat": 12.0}, "player_2": {"name": "David Warner", "player_stat": 44.0}, "stat": "fifties", "skill": "BAT", "question_text": "Who has scored more fifties?", "greater": true}, {"player_1": {"name": "Siddharth Trivedi", "player_stat": 29.29}, "player_2": {"name": "Mustafizur Rahman", "player_stat": 28.54}, "stat": "average", "skill": "BOWL", "question_text": "Who has the lower bowling average?", "greater": false}, {"player_1": {"name": "Morne Morkel", "player_stat": 3.0}, "player_2": {"name": "Brett Lee", "player_stat": 3.0}, "stat": "maidens", "skill": "BOWL", "question_text": "Who has bowled more maidens?", "greater": true}, {"player_1": {"name": "Sanju Samson", "player_stat": 2.0}, "player_2": {"name": "Jason Roy", "player_stat": 0.0}, "stat": "hundreds", "skill": "BAT", "question_text": "Who has scored more hundreds?", "greater": true}, {"player_1": {"name": "Yuvraj Singh", "player_stat": 24.1}, "player_2": {"name": "Mitchell Johnson", "player_stat": 20.1}, "stat": "strike_rate", "skill": "BOWL", "question_text": "Who has the lower bowling strike rate?", "greater": false}, {"player_1": {"name": "Zaheer Khan", "player_stat": 27.27}, "player_2": {"name": "Amit Mishra", "player_stat": 24.31}, "stat": "average", "skill": "BOWL", "question_text": "Who has the lower bowling average?", "greater": false}, {"player_1": {"name": "RP Singh", "player_stat": 7.9}, "player_2": {"name": "Chris Woakes", "player_stat": 9.24}, "stat": "economy", "skill": "BOWL", "question_text": "Who has the lower economy rate?", "greater": false}, {"player_1": {"name": "Sachin Tendulkar", "player_stat": 13.0}, "player_2": {"name": "Travis Head", "player_stat": 1.0}, "stat": "fifties", "skill": "BAT", "question_text": "Who has scored more fifties?", "greater": true}, {"player_1": {"name": "Karn Sharma", "player_stat": 1.0}, "player_2": {"name": "Glenn McGrath", "player_stat": 2.0}, "stat": "maidens", "skill": "BOWL", "question_text": "Who has bowled more maidens?", "greater": true}, {"player_1": {"name": "Mitchell McClenaghan", "player_stat": 17.9}, "player_2": {"name": "Dirk Nannes", "player_stat": 23.0}, "stat": "strike_rate", "skill": "BOWL", "question_text": "Who has the lower bowling strike rate?", "greater": false}, {"player_1": {"name": "Kane Williamson", "player_stat": 110.0}, "player_2": {"name": "David Warner", "player_stat": 461.0}, "stat": "fours", "skill": "BAT", "question_text": "Who has hit more fours?", "greater": true}, {"player_1": {"name": "Shane Watson", "player_stat": 92.0}, "player_2": {"name": "Shadab Jakati", "player_stat": 47.0}, "stat": "wickets", "skill": "BOWL", "question_text": "Who has taken more wickets?", "greater": true}, {"player_1": {"name": "Axar Patel", "player_stat": 2.0}, "player_2": {"name": "Ashish Nehra", "player_stat": 2.0}, "stat": "maidens", "skill": "BOWL", "question_text": "Who has bowled more maidens?", "greater": true}]}