{"questions": [{"player_1": {"name": "Rahul Chahar", "player_stat": 20.1}, "player_2": {"name": "Khaleel Ahmed", "player_stat": 13.9}, "stat": "strike_rate", "skill": "BOWL", "question_text": "Who has the better bowling strike rate?", "greater": false}, {"player_1": {"name": "Khaleel Ahmed", "player_stat": 13.9}, "player_2": {"name": "Samuel Badree", "player_stat": 23.4}, "stat": "strike_rate", "skill": "BOWL", "question_text": "Who has the better bowling strike rate?", "greater": false}, {"player_1": {"name": "Shreyas Gopal", "player_stat": 7.76}, "player_2": {"name": "Vinay Kumar", "player_stat": 8.39}, "stat": "economy", "skill": "BOWL", "question_text": "Who has the better economy rate?", "greater": false}, {"player_1": {"name": "Shahbaz Nadeem", "player_stat": 7.48}, "player_2": {"name": "Dwayne Bravo", "player_stat": 8.39}, "stat": "economy", "skill": "BOWL", "question_text": "Who has the better economy rate?", "greater": false}, {"player_1": {"name": "Ramesh Powar", "player_stat": 40.53}, "player_2": {"name": "Ashok Dinda", "player_stat": 30.04}, "stat": "average", "skill": "BOWL", "question_text": "Who has the better bowling average?", "greater": false}, {"player_1": {"name": "Sreenath Aravind", "player_stat": 8.2}, "player_2": {"name": "Samuel Badree", "player_stat": 7.41}, "stat": "economy", "skill": "BOWL", "question_text": "Who has the better economy rate?", "greater": false}, {"player_1": {"name": "Sarfaraz Khan", "player_stat": 1.0}, "player_2": {"name": "Ashish Reddy", "player_stat": 0.0}, "stat": "zeroes", "skill": "BAT", "question_text": "Who has more ducks?", "greater": true}, {"player_1": {"name": "Johan Botha", "player_stat": 0.0}, "player_2": {"name": "Jaydev Unadkat", "player_stat": 3.0}, "stat": "maidens", "skill": "BOWL", "question_text": "Who has bowled more maidens?", "greater": true}, {"player_1": {"name": "Shaun Marsh", "player_stat": 132.74}, "player_2": {"name": "Quinton de Kock", "player_stat": 132.17}, "stat": "strike_rate", "skill": "BAT", "question_text": "Who has the better batting strike rate?", "greater": true}, {"player_1": {"name": "Lendl Simmons", "player_stat": 11.0}, "player_2": {"name": "Martin Guptill", "player_stat": 1.0}, "stat": "fifties", "skill": "BAT", "question_text": "Who has scored more fifties?", "greater": true}, {"player_1": {"name": "Shane Watson", "player_stat": 7.0}, "player_2": {"name": "Suryakumar Yadav", "player_stat": 4.0}, "stat": "zeroes", "skill": "BAT", "question_text": "Who has more ducks?", "greater": true}, {"player_1": {"name": "Ashish Nehra", "player_stat": 23.53}, "player_2": {"name": "Ramesh Powar", "player_stat": 40.53}, "stat": "average", "skill": "BOWL", "question_text": "Who has the better bowling average?", "greater": false}, {"player_1": {"name": "Ryan ten Doeschate", "player_stat": 1.0}, "player_2": {"name": "David Warner", "player_stat": 45.0}, "stat": "fifties", "skill": "BAT", "question_text": "Who has scored more fifties?", "greater": true}, {"player_1": {"name": "Moeen Ali", "player_stat": 160.41}, "player_2": {"name": "Rohit Sharma", "player_stat": 131.37}, "stat": "strike_rate", "skill": "BAT", "question_text": "Who has the better batting strike rate?", "greater": true}, {"player_1": {"name": "James Faulkner", "player_stat": 1778.0}, "player_2": {"name": "Siddarth Kaul", "player_stat": 1449.0}, "stat": "runs_given", "skill": "BOWL", "question_text": "Who has given away less runs?", "greater": false}, {"player_1": {"name": "Siddharth Trivedi", "player_stat": 29.29}, "player_2": {"name": "Ravichandran Ashwin", "player_stat": 26.27}, "stat": "average", "skill": "BOWL", "question_text": "Who has the better bowling average?", "greater": false}, {"player_1": {"name": "Farveez Maharoof", "player_stat": 0.0}, "player_2": {"name": "Rahul Chahar", "player_stat": 0.0}, "stat": "maidens", "skill": "BOWL", "question_text": "Who has bowled more maidens?", "greater": true}, {"player_1": {"name": "Shubman Gill", "player_stat": 5.0}, "player_2": {"name": "Shikhar Dhawan", "player_stat": 37.0}, "stat": "fifties", "skill": "BAT", "question_text": "Who has scored more fifties?", "greater": true}, {"player_1": {"name": "Ben Rohrer", "player_stat": 137.85}, "player_2": {"name": "Krunal Pandya", "player_stat": 145.52}, "stat": "strike_rate", "skill": "BAT", "question_text": "Who has the better batting strike rate?", "greater": true}, {"player_1": {"name": "Mohammed Shami", "player_stat": 1700.0}, "player_2": {"name": "Pragyan Ojha", "player_stat": 2332.0}, "stat": "runs_given", "skill": "BOWL", "question_text": "Who has given away less runs?", "greater": false}]}