{"questions": [{"player_1": {"name": "Ben Rohrer", "player_stat": 0.0}, "player_2": {"name": "David Warner", "player_stat": 4.0}, "stat": "hundreds", "skill": "BAT", "question_text": "Who has scored more hundreds?", "greater": true}, {"player_1": {"name": "Ryan Harris", "player_stat": 23.26}, "player_2": {"name": "Mohammed Shami", "player_stat": 35.41}, "stat": "average", "skill": "BOWL", "question_text": "Who has the better bowling average?", "greater": false}, {"player_1": {"name": "Andrew Tye", "player_stat": 0.0}, "player_2": {"name": "Dale Steyn", "player_stat": 7.0}, "stat": "maidens", "skill": "BOWL", "question_text": "Who has bowled more maidens?", "greater": true}, {"player_1": {"name": "Sarfaraz Khan", "player_stat": 1.0}, "player_2": {"name": "David Warner", "player_stat": 7.0}, "stat": "zeroes", "skill": "BAT", "question_text": "Who has more ducks?", "greater": true}, {"player_1": {"name": "Roelof van der Merwe", "player_stat": 21.0}, "player_2": {"name": "Farveez Maharoof", "player_stat": 27.0}, "stat": "wickets", "skill": "BOWL", "question_text": "Who has taken more wickets?", "greater": true}, {"player_1": {"name": "Shreyas Gopal", "player_stat": 7.76}, "player_2": {"name": "Sreenath Aravind", "player_stat": 8.2}, "stat": "economy", "skill": "BOWL", "question_text": "Who has the better economy rate?", "greater": false}, {"player_1": {"name": "Dirk Nannes", "player_stat": 28.03}, "player_2": {"name": "Mitchell Starc", "player_stat": 20.38}, "stat": "average", "skill": "BOWL", "question_text": "Who has the better bowling average?", "greater": false}, {"player_1": {"name": "Jos Buttler", "player_stat": 95.0}, "player_2": {"name": "Nitish Rana", "player_stat": 85.0}, "stat": "highest", "skill": "BAT", "question_text": "Who has the greater highest score?", "greater": true}, {"player_1": {"name": "Suryakumar Yadav", "player_stat": 79.0}, "player_2": {"name": "Iqbal Abdulla", "player_stat": 33.0}, "stat": "highest", "skill": "BAT", "question_text": "Who has the greater highest score?", "greater": true}, {"player_1": {"name": "Travis Head", "player_stat": 29.28}, "player_2": {"name": "Quinton de Kock", "player_stat": 29.51}, "stat": "average", "skill": "BAT", "question_text": "Who has the better batting average?", "greater": true}, {"player_1": {"name": "Chris Woakes", "player_stat": 0.0}, "player_2": {"name": "Ravi Rampaul", "player_stat": 4.0}, "stat": "maidens", "skill": "BOWL", "question_text": "Who has bowled more maidens?", "greater": true}, {"player_1": {"name": "Axar Patel", "player_stat": 2193.0}, "player_2": {"name": "Sunil Narine", "player_stat": 2964.0}, "stat": "runs_given", "skill": "BOWL", "question_text": "Who has given away less runs?", "greater": false}, {"player_1": {"name": "Manish Pandey", "player_stat": 121.1}, "player_2": {"name": "Harbhajan Singh", "player_stat": 138.16}, "stat": "strike_rate", "skill": "BAT", "question_text": "Who has the better batting strike rate?", "greater": true}, {"player_1": {"name": "Roelof van der Merwe", "player_stat": 21.0}, "player_2": {"name": "Khaleel Ahmed", "player_stat": 13.9}, "stat": "strike_rate", "skill": "BOWL", "question_text": "Who has the better bowling strike rate?", "greater": false}, {"player_1": {"name": "Piyush Chawla", "player_stat": 7.85}, "player_2": {"name": "Lakshmipathy Balaji", "player_stat": 8.04}, "stat": "economy", "skill": "BOWL", "question_text": "Who has the better economy rate?", "greater": false}, {"player_1": {"name": "Brad Hodge", "player_stat": 125.22}, "player_2": {"name": "Michael Lumb", "player_stat": 143.29}, "stat": "strike_rate", "skill": "BAT", "question_text": "Who has the better batting strike rate?", "greater": true}, {"player_1": {"name": "Praveen Kumar", "player_stat": 90.0}, "player_2": {"name": "Johan Botha", "player_stat": 25.0}, "stat": "wickets", "skill": "BOWL", "question_text": "Who has taken more wickets?", "greater": true}, {"player_1": {"name": "Ajinkya Rahane", "player_stat": 121.92}, "player_2": {"name": "Manoj Tiwary", "player_stat": 116.97}, "stat": "strike_rate", "skill": "BAT", "question_text": "Who has the better batting strike rate?", "greater": true}, {"player_1": {"name": "Ben Hilfenhaus", "player_stat": 16.9}, "player_2": {"name": "Rahul Sharma", "player_stat": 23.2}, "stat": "strike_rate", "skill": "BOWL", "question_text": "Who has the better bowling strike rate?", "greater": false}, {"player_1": {"name": "Krunal Pandya", "player_stat": 88.0}, "player_2": {"name": "Nitish Rana", "player_stat": 98.0}, "stat": "fours", "skill": "BAT", "question_text": "Who has hit more fours?", "greater": true}]}