{"questions": [{"player_1": {"name": "Dirk Nannes", "player_stat": 7.3}, "player_2": {"name": "Ashish Reddy", "player_stat": 9.06}, "stat": "economy", "skill": "BOWL", "question_text": "Who has the better economy rate?", "greater": false}, {"player_1": {"name": "Jacques Kallis", "player_stat": 65.0}, "player_2": {"name": "Iqbal Abdulla", "player_stat": 40.0}, "stat": "wickets", "skill": "BOWL", "question_text": "Who has taken more wickets?", "greater": true}, {"player_1": {"name": "Pragyan Ojha", "player_stat": 2332.0}, "player_2": {"name": "Dimitri Mascarenhas", "player_stat": 356.0}, "stat": "runs_given", "skill": "BOWL", "question_text": "Who has given away less runs?", "greater": false}, {"player_1": {"name": "Michael Hussey", "player_stat": 1.0}, "player_2": {"name": "Rishabh Pant", "player_stat": 1.0}, "stat": "hundreds", "skill": "BAT", "question_text": "Who has scored more hundreds?", "greater": true}, {"player_1": {"name": "Mitchell Starc", "player_stat": 693.0}, "player_2": {"name": "Muttiah Muralitharan", "player_stat": 1696.0}, "stat": "runs_given", "skill": "BOWL", "question_text": "Who has given away less runs?", "greater": false}, {"player_1": {"name": "Chaminda Vaas", "player_stat": 2.0}, "player_2": {"name": "Praveen Kumar", "player_stat": 14.0}, "stat": "maidens", "skill": "BOWL", "question_text": "Who has bowled more maidens?", "greater": true}, {"player_1": {"name": "Murali Kartik", "player_stat": 1388.0}, "player_2": {"name": "Johan Botha", "player_stat": 800.0}, "stat": "runs_given", "skill": "BOWL", "question_text": "Who has given away less runs?", "greater": false}, {"player_1": {"name": "Albie Morkel", "player_stat": 73.0}, "player_2": {"name": "S Badrinath", "player_stat": 71.0}, "stat": "highest", "skill": "BAT", "question_text": "Who has the greater highest score?", "greater": true}, {"player_1": {"name": "Chris Gayle", "player_stat": 7.0}, "player_2": {"name": "Sachin Tendulkar", "player_stat": 4.0}, "stat": "zeroes", "skill": "BAT", "question_text": "Who has more ducks?", "greater": true}, {"player_1": {"name": "Kane Richardson", "player_stat": 0.0}, "player_2": {"name": "Mohit Sharma", "player_stat": 0.0}, "stat": "maidens", "skill": "BOWL", "question_text": "Who has bowled more maidens?", "greater": true}, {"player_1": {"name": "Suresh Raina", "player_stat": 100.0}, "player_2": {"name": "Michael Hussey", "player_stat": 116.0}, "stat": "highest", "skill": "BAT", "question_text": "Who has the greater highest score?", "greater": true}, {"player_1": {"name": "Glenn McGrath", "player_stat": 357.0}, "player_2": {"name": "RP Singh", "player_stat": 2338.0}, "stat": "runs_given", "skill": "BOWL", "question_text": "Who has given away less runs?", "greater": false}, {"player_1": {"name": "Sachin Tendulkar", "player_stat": 1.0}, "player_2": {"name": "Rishabh Pant", "player_stat": 1.0}, "stat": "hundreds", "skill": "BAT", "question_text": "Who has scored more hundreds?", "greater": true}, {"player_1": {"name": "Lendl Simmons", "player_stat": 100.0}, "player_2": {"name": "Jos Buttler", "player_stat": 95.0}, "stat": "highest", "skill": "BAT", "question_text": "Who has the greater highest score?", "greater": true}, {"player_1": {"name": "Ryan Harris", "player_stat": 7.55}, "player_2": {"name": "Jacques Kallis", "player_stat": 7.89}, "stat": "economy", "skill": "BOWL", "question_text": "Who has the better economy rate?", "greater": false}, {"player_1": {"name": "Amit Mishra", "player_stat": 6.0}, "player_2": {"name": "Glenn McGrath", "player_stat": 2.0}, "stat": "maidens", "skill": "BOWL", "question_text": "Who has bowled more maidens?", "greater": true}, {"player_1": {"name": "Shane Watson", "player_stat": 20.0}, "player_2": {"name": "Ashish Reddy", "player_stat": 0.0}, "stat": "fifties", "skill": "BAT", "question_text": "Who has scored more fifties?", "greater": true}, {"player_1": {"name": "Yo Mahesh", "player_stat": 16.1}, "player_2": {"name": "Rahul Chahar", "player_stat": 20.1}, "stat": "strike_rate", "skill": "BOWL", "question_text": "Who has the better bowling strike rate?", "greater": false}, {"player_1": {"name": "Nathan Coulter-Nile", "player_stat": 1.0}, "player_2": {"name": "Siddarth Kaul", "player_stat": 2.0}, "stat": "maidens", "skill": "BOWL", "question_text": "Who has bowled more maidens?", "greater": true}, {"player_1": {"name": "Sunil Narine", "player_stat": 2964.0}, "player_2": {"name": "Yusuf Pathan", "player_stat": 1415.0}, "stat": "runs_given", "skill": "BOWL", "question_text": "Who has given away less runs?", "greater": false}]}