{"questions": [{"player_1": {"name": "Brad Hogg", "player_stat": 24.78}, "player_2": {"name": "Kieron Pollard", "player_stat": 31.42}, "stat": "average", "skill": "BOWL", "question_text": "Who has the lower bowling average?", "greater": false}, {"player_1": {"name": "Siddharth Trivedi", "player_stat": 23.1}, "player_2": {"name": "Jasprit Bumrah", "player_stat": 20.9}, "stat": "strike_rate", "skill": "BOWL", "question_text": "Who has the lower bowling strike rate?", "greater": false}, {"player_1": {"name": "Mitchell Starc", "player_stat": 17.0}, "player_2": {"name": "Kevon Cooper", "player_stat": 17.4}, "stat": "strike_rate", "skill": "BOWL", "question_text": "Who has the lower bowling strike rate?", "greater": false}, {"player_1": {"name": "Andre Russell", "player_stat": 18.6}, "player_2": {"name": "Jasprit Bumrah", "player_stat": 20.9}, "stat": "strike_rate", "skill": "BOWL", "question_text": "Who has the lower bowling strike rate?", "greater": false}, {"player_1": {"name": "James Franklin", "player_stat": 25.0}, "player_2": {"name": "Faf du Plessis", "player_stat": 174.0}, "stat": "fours", "skill": "BAT", "question_text": "Who has hit more fours?", "greater": true}, {"player_1": {"name": "Harbhajan Singh", "player_stat": 15.64}, "player_2": {"name": "James Hopes", "player_stat": 26.06}, "stat": "average", "skill": "BAT", "question_text": "Who has the better batting average?", "greater": true}, {"player_1": {"name": "Ryan ten Doeschate", "player_stat": 23.28}, "player_2": {"name": "Suresh Raina", "player_stat": 33.34}, "stat": "average", "skill": "BAT", "question_text": "Who has the better batting average?", "greater": true}, {"player_1": {"name": "James Faulkner", "player_stat": 46.0}, "player_2": {"name": "Marcus Stoinis", "player_stat": 53.0}, "stat": "highest", "skill": "BAT", "question_text": "Who has the greater highest score?", "greater": true}, {"player_1": {"name": "Sunil Narine", "player_stat": 2898.0}, "player_2": {"name": "Mitchell Starc", "player_stat": 693.0}, "stat": "runs_given", "skill": "BOWL", "question_text": "Who has given away less runs?", "greater": false}, {"player_1": {"name": "Anil Kumble", "player_stat": 6.57}, "player_2": {"name": "Jasprit Bumrah", "player_stat": 7.6}, "stat": "economy", "skill": "BOWL", "question_text": "Who has the lower economy rate?", "greater": false}, {"player_1": {"name": "Ajinkya Rahane", "player_stat": 27.0}, "player_2": {"name": "Ambati Rayudu", "player_stat": 19.0}, "stat": "fifties", "skill": "BAT", "question_text": "Who has scored more fifties?", "greater": true}, {"player_1": {"name": "Jason Roy", "player_stat": 91.0}, "player_2": {"name": "Dwayne Smith", "player_stat": 87.0}, "stat": "highest", "skill": "BAT", "question_text": "Who has the greater highest score?", "greater": true}, {"player_1": {"name": "Zaheer Khan", "player_stat": 7.58}, "player_2": {"name": "Mitchell Marsh", "player_stat": 7.89}, "stat": "economy", "skill": "BOWL", "question_text": "Who has the lower economy rate?", "greater": false}, {"player_1": {"name": "Mohit Sharma", "player_stat": 26.84}, "player_2": {"name": "Jasprit Bumrah", "player_stat": 26.55}, "stat": "average", "skill": "BOWL", "question_text": "Who has the lower bowling average?", "greater": false}, {"player_1": {"name": "Nicholas Pooran", "player_stat": 154.41}, "player_2": {"name": "Michael Lumb", "player_stat": 143.29}, "stat": "strike_rate", "skill": "BAT", "question_text": "Who has the higher strike rate?", "greater": true}, {"player_1": {"name": "Irfan Pathan", "player_stat": 25.5}, "player_2": {"name": "Chris Morris", "player_stat": 18.6}, "stat": "strike_rate", "skill": "BOWL", "question_text": "Who has the lower bowling strike rate?", "greater": false}, {"player_1": {"name": "Kane Williamson", "player_stat": 0.0}, "player_2": {"name": "Sarfaraz Khan", "player_stat": 0.0}, "stat": "hundreds", "skill": "BAT", "question_text": "Who has scored more hundreds?", "greater": true}, {"player_1": {"name": "Michael Lumb", "player_stat": 45.0}, "player_2": {"name": "Chris Lynn", "player_stat": 128.0}, "stat": "fours", "skill": "BAT", "question_text": "Who has hit more fours?", "greater": true}, {"player_1": {"name": "Ashok Dinda", "player_stat": 3.0}, "player_2": {"name": "Amit Mishra", "player_stat": 6.0}, "stat": "maidens", "skill": "BOWL", "question_text": "Who has bowled more maidens?", "greater": true}, {"player_1": {"name": "Rashid Khan", "player_stat": 56.0}, "player_2": {"name": "Mohammad Nabi", "player_stat": 11.0}, "stat": "wickets", "skill": "BOWL", "question_text": "Who has taken more wickets?", "greater": true}]}